Metadata-Version: 1.0
Name: pam-dist
Version: 0.1
Summary: Gaussian distributions
Home-page: UNKNOWN
Author: Pablo Araya-Melo
Author-email: arayamelo.pablo@gmail.com
License: UNKNOWN
Platform: UNKNOWN
